tojson/__init__.py
tojson/csv2json.py
tojson-0.1.0.dist-info/entry_points.txt
tojson-0.1.0.dist-info/LICENSE
tojson-0.1.0.dist-info/WHEEL
tojson-0.1.0.dist-info/METADATA
tojson-0.1.0.dist-info/RECORD
