Metadata-Version: 2.1
Name: tojson
Version: 0.1.0
Summary: A CLI tool to export CSV files to JSON format
License: MIT
Author: Alyetama
Author-email: malyetama@pm.me
Requires-Python: >=3.7,<4.0
Classifier: License :: OSI Approved :: MIT License
Classifier: Programming Language :: Python :: 3
Classifier: Programming Language :: Python :: 3.10
Classifier: Programming Language :: Python :: 3.7
Classifier: Programming Language :: Python :: 3.8
Classifier: Programming Language :: Python :: 3.9
Requires-Dist: numpy (>1.18.0)
Requires-Dist: pandas (>1.0.0)
